antifishpy
