Metadata-Version: 2.1
Name: antifishpy
Version: 1.0.7
Summary: A simple Python module for the Bitflow Anti-Fish API.
Author: Benjamin Churton
License: UNKNOWN
Platform: UNKNOWN
Classifier: Programming Language :: Python :: 3
Classifier: License :: OSI Approved :: MIT License
Classifier: Operating System :: OS Independent
Requires-Python: >=3.6
